SunIdea/.pypirc
SunIdea/__init__.py
SunIdea/sun_config/__init__.py
SunIdea/sun_config/sun_idea_config.py
SunIdea/sun_module/__init__.py
SunIdea/sun_module/multi_task.py
SunIdea/sun_utils/__init__.py
SunIdea/sun_utils/sun_idea_utils.py
sunidea-0.0.4.dist-info/METADATA
sunidea-0.0.4.dist-info/WHEEL
sunidea-0.0.4.dist-info/licenses/LICENSE
sunidea-0.0.4.dist-info/RECORD
